ptstaycool/__init__.py
ptstaycool/__main__.py
ptstaycool/requirements.txt
ptstaycool/core/Hasil.py
ptstaycool/core/Main.py
ptstaycool-4.0.9.dist-info/LICENSE
ptstaycool-4.0.9.dist-info/METADATA
ptstaycool-4.0.9.dist-info/WHEEL
ptstaycool-4.0.9.dist-info/top_level.txt
ptstaycool-4.0.9.dist-info/RECORD
