Metadata-Version: 2.1
Name: ptstaycool
Version: 4.0.9
Summary: Tugas kelompok 9
Home-page: https://github.com/dafaprasetya/HonorKaryawanPython
Author: kelompok9
Author-email: octocadal234@gmail.com
Project-URL: Bug Tracker, https://github.com/pypa/sampleproject/issues
Classifier: Programming Language :: Python :: 3
Classifier: License :: OSI Approved :: MIT License
Classifier: Operating System :: OS Independent
Requires-Python: >=3.6
License-File: LICENSE
Requires-Dist: pandas
